README.md
setup.py
rudeencrypt/__init__.py
rudeencrypt/rudeencrypt.py
rudeencrypt.egg-info/PKG-INFO
rudeencrypt.egg-info/SOURCES.txt
rudeencrypt.egg-info/dependency_links.txt
rudeencrypt.egg-info/requires.txt
rudeencrypt.egg-info/top_level.txt
rudeencrypt/test/__init__.py