Metadata-Version: 2.1
Name: rudeencrypt
Version: 2021.3.13.1253
Summary: A simple API used to encrypt the python dict into a file using AES256.
Home-page: https://github.com/HengyueLi/rudeencrypt
Author: Hengyue Li
Author-email: hengyue.li@hengyue.li
License: LICENSE.md
Platform: UNKNOWN
Requires-Python: >=3.5
